AUTHORS.rst
CONTRIBUTING.rst
HISTORY.rst
LICENSE
MANIFEST.in
README.rst
setup.cfg
setup.py
docs/Makefile
docs/authors.rst
docs/conf.py
docs/contributing.rst
docs/history.rst
docs/index.rst
docs/installation.rst
docs/make.bat
docs/modules.rst
docs/readme.rst
docs/tushare_easy.consts.rst
docs/tushare_easy.getdata.rst
docs/tushare_easy.rst
docs/tushare_easy.utils.rst
docs/_build/html/_static/ajax-loader.gif
docs/_build/html/_static/comment-bright.png
docs/_build/html/_static/comment-close.png
docs/_build/html/_static/comment.png
docs/_build/html/_static/down-pressed.png
docs/_build/html/_static/down.png
docs/_build/html/_static/file.png
docs/_build/html/_static/minus.png
docs/_build/html/_static/plus.png
docs/_build/html/_static/up-pressed.png
docs/_build/html/_static/up.png
docs/_theme/scipy/static/img/glyphicons-halflings-white.png
docs/_theme/scipy/static/img/glyphicons-halflings.png
scripts/tushare_easy
tests/__init__.py
tests/test_tushare_easy.py
tushare_easy/__init__.py
tushare_easy/consts.py
tushare_easy/getdata.py
tushare_easy/utils.py
tushare_easy.egg-info/PKG-INFO
tushare_easy.egg-info/SOURCES.txt
tushare_easy.egg-info/dependency_links.txt
tushare_easy.egg-info/not-zip-safe
tushare_easy.egg-info/top_level.txt