Metadata-Version: 1.1
Name: tushare-easy
Version: 0.1.1
Summary: make tushare easyer
Home-page: https://github.com/yingnn/tushare_easy
Author: yingnn
Author-email: yingnn@live.cn
License: MIT license
Keywords: tushare_easy,tushare
Platform: UNKNOWN
Classifier: Development Status :: 2 - Pre-Alpha
Classifier: Intended Audience :: Developers
Classifier: License :: OSI Approved :: MIT License
Classifier: Natural Language :: English
Classifier: Programming Language :: Python :: 2.7
Classifier: Programming Language :: Python :: 3.3
